mineatar/__init__.py
mineatar/client.py
mineatar/exceptions.py
py_mineatar-1.0.2.dist-info/licenses/LICENSE
py_mineatar-1.0.2.dist-info/METADATA
py_mineatar-1.0.2.dist-info/WHEEL
py_mineatar-1.0.2.dist-info/top_level.txt
py_mineatar-1.0.2.dist-info/RECORD
