Metadata-Version: 2.4
Name: py-mineatar
Version: 1.0.2
Summary: A Python wrapper for the Mineatar API.
Author-email: Rezn1r <rezn1r@proton.me>
License-Expression: MIT
Project-URL: Homepage, https://github.com/Rezn1r/py-mineatar
Keywords: mineatar,minecraft,api,wrapper
Classifier: Programming Language :: Python :: 3.11
Classifier: Programming Language :: Python :: 3.12
Classifier: Operating System :: OS Independent
Requires-Python: >=3.11
License-File: LICENSE
Requires-Dist: aiohttp>=3.13.2
Requires-Dist: requests>=2.32.5
Dynamic: license-file
